transformer_serving/__init__.py
transformer_serving/server/__init__.py
transformer_serving/server/benchmark.py
transformer_serving/server/graph.py
transformer_serving/server/helper.py
transformer_serving/server/http.py
transformer_serving/server/model_config.py
transformer_serving/server/zmq_decor.py
transformer_serving/server/cli/__init__.py
transformer_as_service-1.13.5.dist-info/METADATA
transformer_as_service-1.13.5.dist-info/WHEEL
transformer_as_service-1.13.5.dist-info/entry_points.txt
transformer_as_service-1.13.5.dist-info/top_level.txt
transformer_as_service-1.13.5.dist-info/RECORD
